COPYRIGHT.txt
LICENSE.txt
MANIFEST.in
README.md
requirements.txt
setup.cfg
setup.py
versioneer.py
splash_ingest/__init__.py
splash_ingest/_version.py
splash_ingest/handlers.py
splash_ingest/model.py
splash_ingest.egg-info/PKG-INFO
splash_ingest.egg-info/SOURCES.txt
splash_ingest.egg-info/dependency_links.txt
splash_ingest.egg-info/entry_points.txt
splash_ingest.egg-info/requires.txt
splash_ingest.egg-info/top_level.txt
splash_ingest/tests/__init__.py
splash_ingest/tests/test_handlers.py
splash_ingest/tests/test_mapping_ingestor.py