Metadata-Version: 2.1
Name: splash-ingest
Version: 0.1.3
Summary: Different ingestors used in Splash
Home-page: https://github.com/als-computing/splash-ingest
Author: ALS Computing Group
Author-email: dmcreynolds@lbl.gov
License: BSD (3-clause)
Download-URL: https://github.com/als-computing/splash-ingest/archive/v0.1.1.tar.gzz
Platform: UNKNOWN
Classifier: Development Status :: 3 - Alpha
Classifier: Natural Language :: English
Classifier: Programming Language :: Python :: 3
Classifier: License :: OSI Approved :: BSD License
Requires-Python: >=3.7
